fastcolors/__init__.py
fastcolors/constants.py
fastcolors/py.typed
fast_colors-1.0.1.dist-info/METADATA
fast_colors-1.0.1.dist-info/WHEEL
fast_colors-1.0.1.dist-info/top_level.txt
fast_colors-1.0.1.dist-info/RECORD
