Metadata-Version: 2.4
Name: fast-colors
Version: 1.0.1
Summary: A simple and lightweight module for coloring your texts.
Author-email: Lag3n <fast-colors.devotion971@passmail.com>
License: MIT
Project-URL: Homepage, https://github.com/iLag3n/fast-colors
Requires-Python: >=3.7
